rabbitmq_client/__init__.py
rabbitmq_client/connection.py
rabbitmq_client/consumer.py
rabbitmq_client/defs.py
rabbitmq_client/producer.py
rabbitmq_client-2.4.0.dist-info/LICENSE
rabbitmq_client-2.4.0.dist-info/METADATA
rabbitmq_client-2.4.0.dist-info/WHEEL
rabbitmq_client-2.4.0.dist-info/top_level.txt
rabbitmq_client-2.4.0.dist-info/RECORD
