Metadata-Version: 2.1
Name: rabbitmq-client
Version: 2.4.0
Summary: RabbitMQ client based on the pika library.
Home-page: https://github.com/maansthoernvik/rabbitmq_client
Author: Måns Thörnvik
Author-email: thornvik.mans@gmail.com
License: MIT
Platform: UNKNOWN
Classifier: License :: OSI Approved :: MIT License
Classifier: Programming Language :: Python
Classifier: Programming Language :: Python :: 3
Classifier: Programming Language :: Python :: 3.6
Classifier: Programming Language :: Python :: Implementation :: CPython
Classifier: Programming Language :: Python :: Implementation :: PyPy
Requires-Python: >=3.6.0
Requires-Dist: pika
